{"mainCat": "101", "subCatCode": "258", "title": "구미 코스닥 상장사 절반 이상 작년 매출 감소", "body": "// flash 오류를 우회하기 위한 함수 추가\nfunction _flash_removeCallback() {}\n\n구미상공회의소[연합뉴스 자료사진]    (구미=연합뉴스) 홍창진 기자 = 지난해 경북 구미에 본사를 둔 코스닥 상장사 중 절반 이상이 매출액 감소를 겪은 것으로 나타났다.    구미상공회의소는 21일 한국거래소와 전자공시시스템 자료를 바탕으로 이 같은 2020년 경영실적 분석 결과를 발표했다.    18개 코스닥 상장사 가운데 2019년보다 매출액이 늘어난 회사는 8곳, 줄어든 회는 10곳인 것으로 조사됐다.    그러나 18개사 총매출액은 1조7천252억원으로 전년 1조5천117억원보다 14.1% 증가했다.    총영업이익은 1천637억원으로 전년 896억원보다 82.7%나 증가했다.    그러나 총당기순이익은 318억원으로 전년 586억원 대비 45.7% 감소했다.    기업별 당기순이익은 6곳이 흑자 지속, 3곳이 흑자 전환, 6곳이 적자 전환, 3곳이 적자 지속으로 나타났다.     윤재호 구미상의 회장은 \"지난해 반도체 부품, 나노기술 분야, 자동화장비 등 분야 매출 및 영업이익이 크게 늘었다\"며 \"정부가 신성장산업 시장 규모 확대에 발맞춰 수도권 기업의 지방투자를 유도해야 한다\"고 말했다.    realism@yna.co.kr▶네이버에서도 뉴스는 연합뉴스[구독 클릭]▶[팩트체크] 남녀 징병국가 현실은?▶제보하기", "date": "2021.04.21. 오후 4:23", "source": "연합뉴스"}