{"mainCat": "101", "subCatCode": "258", "title": "[공시]신영증권, 자기주식 우선주 5만주 장내 매수 결정", "body": "// flash 오류를 우회하기 위한 함수 추가\nfunction _flash_removeCallback() {}\n\n\t\n\t  [파이낸셜뉴스] 신영증권은 자기주식 우선주 5만주를 장내 매수하기로 결정했고 21일 공시했다.   취득 예정금액은 28억6500만원이다. 향후 주가 변동에 따라 실제 취득금액은 변동될 수 있다. 취득 예상기간은 2021년 4월 22일부터 7월 21일까지다.    ggg@fnnews.com 강구귀 기자   ▶ 헉! 소리나는 스!토리 뉴스 [헉스] / ▶ 너 그거 아니? [두유노우]▶ 날로먹고 구워먹는 금융이슈 [파인애플] / ▶ 모(毛)아 모아 [모아시스]  ※ 저작권자 ⓒ 파이낸셜뉴스. 무단 전재-재배포 금지", "date": "2021.04.21. 오후 5:22", "source": "파이낸셜뉴스"}