{"mainCat": "101", "subCatCode": "259", "title": "우리금융, 깜짝실적에 사상최대 '축포'…1Q 순익 6716억", "body": "// flash 오류를 우회하기 위한 함수 추가\nfunction _flash_removeCallback() {}\n\n시장 추정치 20% 웃돌아…\"비은행 부문 실적 기여\"서울 중구 우리금융그룹 본사 [사진=뉴시스][아이뉴스24 서상혁 기자] 우리금융지주는 올 1분기 6천716억원의 당기순익을 올렸다고 21일 밝혔다.전년 동기 대비 29.7%, 전 분기 대비 300% 이상 증가한 수치로 지주사 전환 이후 사상 최대 분기 실적이다.1분기 우리금융의 실적은 시장 추정치도 훨씬 웃도는 '어닝 서프라이즈(깜짝실적)'였다. 증권정보업체 에프엔가이드에 따르면 우리금융 1분기 실적에 대한 증권사 평균 추정치(컨센서스)는 5천608억원으로, 실제 실적은 이보다 19.7% 높았다.이자이익과 비이자이익을 합한 순영업수익은 1조9천870억원으로, 전분기 대비 17.0% 증가했다. 이자이익은 1조6천196억원으로 기업대출 중심의 자산 성장과 저비용성 예금 증대 등 순이자마진 개선 노력으로 3% 이상 증가했다는 설명이다.우리금융은 '깜짝 실적'의 배경에 대해 \"수익구조 개선과 리스크 관리에 그룹 역량을 집중하고, 지주 전환 이후 비은행 포트폴리오를 확충해가며 수익 기반을 확대한 결과\"라고 밝혔다.실제 우리금융의 비이자이익은 자산관리와 유가증권 부문 호조에 캐피탈의 리스 수수료 등이 더해지며 3천674억원을 시현했다.고정이하여신비율(NPL)은 0.39%로 전년 말 대비 개선됐고, 연체율도 0.27%로 양호한 수준이다. 우량자산비율과 NPL커버리지비율은 각각 88.2%, 162.2%를 기록하며 미래 불확실성에도 충분한 손실 흡수 능력을 확보했다고 회사 측은 설명했다.판매관리비용률은 46.2%로 전년 동기 대비 4%포인트(p) 개선됐다.주요 자회사별 연결 당기순익은 ▲우리은행 5천894억원 ▲우리카드 720억원 ▲우리금융캐피탈 350억원 ▲우리종합금융 170억원이다.우리금융지주 관계자는 \"이번 분기 실적발표를 통해 우리금융의 개선된 이익창출력과 더욱 견조해진 펀더멘털을 확인할 수 있었다\"라며 \"특히 비은행 부문 손익이 이번 분기에 처음으로 1천억원을 넘어서면서 신규 편입된 자회사들의 손익기여 효과가 본격화되고 있고, 은행의 수익성 개선까지 더해지면서 우리금융의 실적 개선 모멘텀은 연중 지속될 것\"이라고 말했다.이어 \"지난 정기주주총회에서 밝힌 것처럼 코로나19 안정화시 다양하고 적극적인 주주환원정책을 추진할 예정이며, 환경·사회·지배구조(ESG) 부문에도 박차를 가해 지속가능 경영체제를 속도감 있게 구축해 나갈 것\"이라고 밝혔다./서상혁 기자(hyuk@inews24.com)▶네이버 채널에서 '아이뉴스24'를 구독해주세요.▶재밌는 아이뉴스TV 영상보기 ▶아이뉴스24 바로가기[ⓒ 아이뉴스24 무단전재 및 재배포 금지]", "date": "2021.04.21. 오후 4:00", "source": "아이뉴스24"}